picwish/__init__.py
picwish/enums.py
picwish/image_models.py
picwish/main.py
picwish/signature.py
picwish-0.6.0.dist-info/LICENSE
picwish-0.6.0.dist-info/METADATA
picwish-0.6.0.dist-info/WHEEL
picwish-0.6.0.dist-info/top_level.txt
picwish-0.6.0.dist-info/RECORD
