Metadata-Version: 2.1
Name: picwish
Version: 0.6.0
Summary: Picwish Photo Enhancer
Home-page: https://github.com/d60/picwish
License: MIT
Requires-Python: >=3.10
License-File: LICENSE
Requires-Dist: httpx
Requires-Dist: filetype
